colorterminal/__init__.py
colorterminal/ascii_art/__init__.py
colorterminal/ascii_art/image_converter.py
colorterminal/ascii_art/text_art.py
colorterminal/printers/__init__.py
colorterminal/printers/base.py
colorterminal/printers/semantic.py
colorterminal/printers/style.py
colorterminal/progress_bars/__init__.py
colorterminal/progress_bars/animated.py
colorterminal/progress_bars/base.py
colorterminal/progress_bars/multi.py
colorterminal/progress_bars/spinner.py
colorterminal/shapes/__init__.py
colorterminal/shapes/base.py
colorterminal/shapes/box.py
colorterminal/shapes/circle.py
colorterminal/shapes/diamond.py
colorterminal/shapes/line.py
colorterminal/shapes/rectangle.py
colorterminal/shapes/triangle.py
colorterminal/tables/__init__.py
colorterminal/tables/base.py
colorterminal/tables/colored.py
colorterminal/tables/grid.py
terminal_colorize-2.0.2.dist-info/licenses/LICENSE
terminal_colorize-2.0.2.dist-info/METADATA
terminal_colorize-2.0.2.dist-info/WHEEL
terminal_colorize-2.0.2.dist-info/top_level.txt
terminal_colorize-2.0.2.dist-info/RECORD
