Metadata-Version: 2.4
Name: terminal-colorize
Version: 2.0.2
Summary: A comprehensive library for colored terminal output, progress bars, tables, and shapes using ANSI escape codes
Home-page: https://github.com/mmssajith/colorterm
Author: Mohamed Sajith
Author-email: Mohamed Sajith <mmssajith@gmail.com>
Maintainer-email: Mohamed Sajith <mmssajith@gmail.com>
License-Expression: MIT
Project-URL: Homepage, https://github.com/mmssajith/colorterm
Project-URL: Documentation, https://github.com/mmssajith/colorterm#readme
Project-URL: Repository, https://github.com/mmssajith/colorterm
Project-URL: Bug Reports, https://github.com/mmssajith/colorterm/issues
Project-URL: Source, https://github.com/mmssajith/colorterm
Project-URL: Changelog, https://github.com/mmssajith/colorterm/blob/main/CHANGELOG.md
Keywords: terminal,color,ansi,cli,colored,output,styling,progress,progressbar,table,shapes,ascii-art,console,terminal-colors,terminal-styling,text-formatting,dashboard
Classifier: Development Status :: 5 - Production/Stable
Classifier: Intended Audience :: Developers
Classifier: Topic :: Software Development :: Libraries :: Python Modules
Classifier: Topic :: Terminals
Classifier: Topic :: Software Development :: User Interfaces
Classifier: Programming Language :: Python :: 3
Classifier: Programming Language :: Python :: 3.8
Classifier: Programming Language :: Python :: 3.9
Classifier: Programming Language :: Python :: 3.10
Classifier: Programming Language :: Python :: 3.11
Classifier: Programming Language :: Python :: 3.12
Classifier: Programming Language :: Python :: 3.13
Classifier: Operating System :: OS Independent
Classifier: Operating System :: POSIX :: Linux
Classifier: Operating System :: MacOS
Classifier: Operating System :: Microsoft :: Windows
Classifier: Environment :: Console
Classifier: Natural Language :: English
Classifier: Typing :: Typed
Requires-Python: >=3.8
License-File: LICENSE
Provides-Extra: dev
Requires-Dist: pytest>=7.0.0; extra == "dev"
Requires-Dist: pytest-cov>=4.0.0; extra == "dev"
Requires-Dist: black>=22.0.0; extra == "dev"
Requires-Dist: ruff>=0.1.0; extra == "dev"
Requires-Dist: mypy>=1.0.0; extra == "dev"
Requires-Dist: pre-commit>=3.0.0; extra == "dev"
Requires-Dist: isort>=5.12.0; extra == "dev"
Requires-Dist: bandit>=1.7.0; extra == "dev"
Requires-Dist: pydocstyle>=6.3.0; extra == "dev"
Provides-Extra: ascii
Requires-Dist: numpy>=1.19.0; extra == "ascii"
Requires-Dist: Pillow>=8.0.0; extra == "ascii"
Dynamic: author
Dynamic: home-page
Dynamic: license-file
Dynamic: requires-python
